{"ClassId":10720,"ClassDataType":"othliab_pos_98-07","PaidTriangle":{"Name":"10720_Paid","TriangleValues":[[1998,[2,2,2,2,2,2,2,2,2,2]],[1999,[0,0,0,0,0,0,0,0,0]],[2000,[0,0,0,0,0,0,0,0]],[2001,[0,0,0,0,0,0,0]],[2002,[0,0,0,0,0,0]],[2003,[0,0,0,0,0]],[2004,[0,0,0,0]],[2005,[0,1,1]],[2006,[1,1]],[2007,[0]]],"FilteredTransactions":{"Name":"","Values":[]},"ExcludeData":[],"OriginPeriodicity":1,"DevelopmentRatio":1,"ShiftOrigin":0,"IsIncremental":false,"PriorOrigin":null,"IsInflated":false},"IncurredTriangle":{"Name":"10720_Incurred","TriangleValues":[[1998,[2,2,2,2,2,2,2,2,2,2]],[1999,[0,0,0,0,0,0,0,0,0]],[2000,[1,0,0,0,0,0,0,0]],[2001,[0,0,0,0,0,0,0]],[2002,[0,0,0,0,0,0]],[2003,[0,0,0,0,0]],[2004,[0,0,0,0]],[2005,[0,1,1]],[2006,[1,1]],[2007,[0]]],"FilteredTransactions":{"Name":"","Values":[]},"ExcludeData":[],"OriginPeriodicity":1,"DevelopmentRatio":1,"ShiftOrigin":0,"IsIncremental":false,"PriorOrigin":null,"IsInflated":false},"FuturePaid":[[1998,[]],[1999,[0]],[2000,[0,0]],[2001,[0,0,0]],[2002,[0,0,0,0]],[2003,[0,0,0,0,0]],[2004,[0,0,0,0,0,0]],[2005,[0,0,0,0,0,0,0]],[2006,[0,0,0,0,0,0,0,0]],[2007,[0,0,0,0,0,0,0,0,0]]],"FutureIncurred":[[1998,[]],[1999,[0]],[2000,[0,0]],[2001,[0,0,0]],[2002,[0,0,0,0]],[2003,[0,0,0,0,0]],[2004,[0,0,0,0,0,0]],[2005,[0,0,0,0,0,0,0]],[2006,[0,0,0,0,0,0,0,0]],[2007,[0,0,0,0,0,0,0,0,0]]],"EarnedPremium":[[1998,41],[1999,92],[2000,112],[2001,53],[2002,21],[2003,22],[2004,23],[2005,23],[2006,19],[2007,28]]}