{"ClassId":15768,"ClassDataType":"othliab_pos_98-07","PaidTriangle":{"Name":"15768_Paid","TriangleValues":[[1998,[12,17,21,22,22,24,24,24,24,24]],[1999,[2,4,6,9,9,9,9,9,9]],[2000,[3,4,14,16,19,19,19,19]],[2001,[0,4,7,10,10,10,10]],[2002,[0,2,17,18,21,32]],[2003,[6,10,19,19,19]],[2004,[5,11,11,11]],[2005,[8,13,37]],[2006,[3,4]],[2007,[1]]],"FilteredTransactions":{"Name":"","Values":[]},"ExcludeData":[],"OriginPeriodicity":1,"DevelopmentRatio":1,"ShiftOrigin":0,"IsIncremental":false,"PriorOrigin":null,"IsInflated":false},"IncurredTriangle":{"Name":"15768_Incurred","TriangleValues":[[1998,[42,23,26,25,23,24,24,24,24,24]],[1999,[30,16,12,11,10,9,9,9,9]],[2000,[44,11,23,20,22,19,19,19]],[2001,[18,11,10,18,10,10,10]],[2002,[28,27,35,32,92,92]],[2003,[41,43,19,19,19]],[2004,[50,11,11,11]],[2005,[47,154,87]],[2006,[5,13]],[2007,[51]]],"FilteredTransactions":{"Name":"","Values":[]},"ExcludeData":[],"OriginPeriodicity":1,"DevelopmentRatio":1,"ShiftOrigin":0,"IsIncremental":false,"PriorOrigin":null,"IsInflated":false},"FuturePaid":[[1998,[]],[1999,[0]],[2000,[0,0]],[2001,[0,0,0]],[2002,[30,4,0,0]],[2003,[0,0,0,0,0]],[2004,[2,0,0,0,0,0]],[2005,[43,0,0,0,0,0,0]],[2006,[0,0,0,0,2,0,0,0]],[2007,[6,59,26,1,0,0,0,0,0]]],"FutureIncurred":[[1998,[]],[1999,[0]],[2000,[0,0]],[2001,[0,0,0]],[2002,[-27,1,0,0]],[2003,[0,0,0,0,0]],[2004,[2,0,0,0,0,0]],[2005,[-7,0,0,0,0,0,0]],[2006,[1,-10,0,0,2,0,0,0]],[2007,[79,-64,33,-6,0,0,0,0,0]]],"EarnedPremium":[[1998,107],[1999,90],[2000,91],[2001,79],[2002,90],[2003,197],[2004,152],[2005,131],[2006,126],[2007,123]]}